dermahelpr/__init__.py
dermahelpr/format_response.py
dermahelpr-0.0.2.dist-info/LICENSE
dermahelpr-0.0.2.dist-info/METADATA
dermahelpr-0.0.2.dist-info/WHEEL
dermahelpr-0.0.2.dist-info/top_level.txt
dermahelpr-0.0.2.dist-info/RECORD
