Metadata-Version: 2.1
Name: dermahelpr
Version: 0.0.2
Summary: A Python package to help you with your daily tasks
Home-page: https://github.com/clinikally/dermahelpr
Author: Clinikally
Author-email: kshitijsrivastava@clinikally.com
License: MIT license
Platform: UNKNOWN
Classifier: Programming Language :: Python :: 3
Classifier: License :: OSI Approved :: MIT License
Classifier: Operating System :: OS Independent
Requires-Python: >=3.6
License-File: LICENSE
Requires-Dist: fastapi==0.115.6
Requires-Dist: typing-extensions==4.12.2
Requires-Dist: python-semantic-release>=8.3.0
Requires-Dist: wheel>=0.42.0
Requires-Dist: setuptools-scm>=6.2
